ChadBot/__init__.py
ChadBot/chadBot.py
ChadBot/test.py
ChadBot/core/FAQ.py
ChadBot/core/__init__.py
ChadBot/core/defaults.py
ChadBot/core/exceptions.py
ChadBot/core/generation.py
ChadBot/core/utils.py
ChadBot/generation/__init__.py
ChadBot/generation/rajat_work/__init__.py
ChadBot/generation/rajat_work/qgen/__init__.py
ChadBot/generation/rajat_work/qgen/encoder/__init__.py
ChadBot/generation/rajat_work/qgen/encoder/base.py
ChadBot/generation/rajat_work/qgen/encoder/dummy.py
ChadBot/generation/rajat_work/qgen/encoder/fasttext.py
ChadBot/generation/rajat_work/qgen/encoder/glove.py
ChadBot/generation/rajat_work/qgen/generator/__init__.py
ChadBot/generation/rajat_work/qgen/generator/base.py
ChadBot/generation/rajat_work/qgen/generator/eda.py
ChadBot/generation/rajat_work/qgen/generator/imt.py
ChadBot/generation/rajat_work/qgen/generator/symsub.py
ChadBot/generation/rajat_work/qgen/generator/zeroshot.py
ChadBot/generation/rajat_work/qgen/generator/fpm/__init__.py
ChadBot/generation/rajat_work/qgen/generator/fpm/fpm.py
ChadBot/generation/rajat_work/qgen/generator/fpm/matcher.py
ChadBot/generation/rajat_work/qgen/generator/fpm/pattern.py
ChadBot/generation/rajat_work/qgen/util/__init__.py
ChadBot/generation/rajat_work/qgen/util/config.py
ChadBot/generation/rajat_work/qgen/util/file.py
ChadBot/generation/rajat_work/qgen/util/nlp.py
ChadBot/generation/sentAug/__init__.py
ChadBot/generation/sentAug/sentAug.py
ChadBot/modelRelated/__init__.py
ChadBot/modelRelated/config.py
ChadBot/modelRelated/utils.py
ChadBot5-0.1.dist-info/LICENSE
ChadBot5-0.1.dist-info/METADATA
ChadBot5-0.1.dist-info/WHEEL
ChadBot5-0.1.dist-info/top_level.txt
ChadBot5-0.1.dist-info/RECORD
